setup.py
acollections/__init__.py
acollections.egg-info/PKG-INFO
acollections.egg-info/SOURCES.txt
acollections.egg-info/dependency_links.txt
acollections.egg-info/not-zip-safe
acollections.egg-info/top_level.txt