Metadata-Version: 1.0
Name: acollections
Version: 0.1
Summary: Advanced storage classes
Home-page: UNKNOWN
Author: Jakub Chronowski
Author-email: chrnwsk@gmail.com
License: MIT
Platform: UNKNOWN
